psdelivery/__init__.py
psdelivery/__main__.py
psdelivery/command_line.py
psdelivery/controller.py
psdelivery/core/crawler.py
psdelivery/core/difficulty.py
psdelivery/core/engine.py
psdelivery/core/item.py
psdelivery/core/option.py
psdelivery/crawlers/baekjoon/__init__.py
psdelivery/crawlers/baekjoon/crawler.py
psdelivery/crawlers/baekjoon/difficulty.py
psdelivery/crawlers/baekjoon/item.py
psdelivery/crawlers/leetcode/__init__.py
psdelivery/crawlers/leetcode/crawler.py
psdelivery/crawlers/leetcode/difficulty.py
psdelivery/crawlers/leetcode/item.py
psdelivery/exc.py
psdelivery/utils/logger.py
psdelivery/utils/type_checker.py
psdelivery-0.1.2.dist-info/LICENSE
psdelivery-0.1.2.dist-info/METADATA
psdelivery-0.1.2.dist-info/WHEEL
psdelivery-0.1.2.dist-info/RECORD
