Metadata-Version: 2.1
Name: psdelivery
Version: 0.1.2
Summary: The simple crawler about algorithm problem service website
Home-page: https://github.com/team-angeline/psdelivery
License: GPL-3.0-only
Keywords: crwaler,problem-solving
Author: recoma
Author-email: seokbong60@gmail.com
Requires-Python: >=3.10,<4.0
Classifier: Intended Audience :: Developers
Classifier: License :: OSI Approved :: GNU General Public License v3 (GPLv3)
Classifier: Operating System :: Microsoft :: Windows :: Windows 10
Classifier: Operating System :: POSIX :: Linux
Classifier: Programming Language :: Python :: 3
Classifier: Programming Language :: Python :: 3.10
Classifier: Programming Language :: Python :: 3.11
Classifier: Programming Language :: Python :: 3
Classifier: Programming Language :: Python :: 3 :: Only
Classifier: Programming Language :: Python :: 3.10
Classifier: Programming Language :: Python :: 3.11
Classifier: Topic :: Software Development :: Libraries :: Python Modules
Requires-Dist: beautifulsoup4 (>=4.12.2,<5.0.0)
Requires-Dist: requests (>=2.28.2,<3.0.0)
Requires-Dist: selenium (>=4.9.0,<5.0.0)
Requires-Dist: webdriver-manager (>=3.8.6,<4.0.0)
Project-URL: Repository, https://github.com/team-angeline/psdelivery
